sparse_array/matrix.py
sparse_array/vector.py
sparse_array/_core.pyi
sparse_array/_core.cpp
sparse_array/__init__.py
sparse_array/py.typed
sparse_array/array.py
sparse_array/_core.cpython-314t-darwin.so
disco_sparse_array-0.1.1.dist-info/RECORD
disco_sparse_array-0.1.1.dist-info/WHEEL
disco_sparse_array-0.1.1.dist-info/METADATA
disco_sparse_array-0.1.1.dist-info/licenses/LICENSE
