Metadata-Version: 2.2
Name: disco-sparse-array
Version: 0.1.1
Summary: Sparse vector and matrix classes with fast operations for Disco simulations
Author: Michiel Jansen
License: MIT
Classifier: License :: OSI Approved :: MIT License
Classifier: Programming Language :: Python :: 3
Classifier: Programming Language :: Python :: 3 :: Only
Classifier: Programming Language :: Python :: 3.11
Classifier: Programming Language :: Python :: 3.12
Classifier: Programming Language :: Python :: 3.13
Classifier: Programming Language :: C++
Classifier: Operating System :: OS Independent
Requires-Python: >=3.11
Requires-Dist: numpy>=1.23
Requires-Dist: pandas>=2.3
Provides-Extra: dev
Requires-Dist: pytest>=8; extra == "dev"
Requires-Dist: pytest-cov>=5; extra == "dev"
Requires-Dist: mypy>=1.10; extra == "dev"
Requires-Dist: cibuildwheel>=2.20; extra == "dev"
Requires-Dist: pybind11-stubgen>=2.5; extra == "dev"
